parascore/__init__.py
parascore/score.py
parascore/scorer.py
parascore/utils.py
parascore-1.0.5.dist-info/METADATA
parascore-1.0.5.dist-info/WHEEL
parascore-1.0.5.dist-info/license.txt
parascore-1.0.5.dist-info/top_level.txt
parascore-1.0.5.dist-info/RECORD
